taichi_three/__init__.py
taichi_three/__main__.py
taichi_three/buffer.py
taichi_three/camera.py
taichi_three/common.py
taichi_three/geometry.py
taichi_three/interme.py
taichi_three/light.py
taichi_three/loader.py
taichi_three/mciso.py
taichi_three/model.py
taichi_three/objedit.py
taichi_three/raycast.py
taichi_three/scatter.py
taichi_three/scene.py
taichi_three/shading.py
taichi_three/skybox.py
taichi_three/transform.py
taichi_three-0.0.9.dist-info/LICENSE
taichi_three-0.0.9.dist-info/METADATA
taichi_three-0.0.9.dist-info/WHEEL
taichi_three-0.0.9.dist-info/top_level.txt
taichi_three-0.0.9.dist-info/RECORD
