Metadata-Version: 2.1
Name: taichi-three
Version: 0.0.9
Summary: A Taichi extension library to render 3D scenes
Home-page: https://github.com/taichi-dev/taichi_three
Author: 彭于斌
Author-email: 1931127624@qq.com
License: MIT
Keywords: graphics,renderer
Platform: UNKNOWN
Classifier: Intended Audience :: Developers
Classifier: Intended Audience :: Science/Research
Classifier: Topic :: Multimedia :: Graphics
Classifier: Topic :: Games/Entertainment :: Simulation
Classifier: Operating System :: OS Independent
Requires-Python: >=3.6
Requires-Dist: taichi (>=0.6.38)
Requires-Dist: taichi-glsl (>=0.0.10)
